[
  {
    "關係代號": "LH_商標法_施行細則",
    "主法規": "商標法",
    "關聯法規": "商標法施行細則",
    "階層關係類型": "子法規",
    "關聯說明": "商標法第一百一十條授權主管機關訂定施行細則，詳細規範本法之施行細節。",
    "台灣觀點": "在台灣的法規體系中，施行細則扮演著補充母法、提供具體執行依據的角色。商標法施行細則與商標法母法共同構成完整的商標法規範體系，實務上兩者必須互相參照適用。"
  },
  {
    "關係代號": "LH_商標法_代理人辦法",
    "主法規": "商標法",
    "關聯法規": "商標代理人相關辦法",
    "階層關係類型": "下位行政規則",
    "關聯說明": "商標法第六條第四項授權主管機關訂定辦法，規範商標代理人之資格、考試、登錄、管理等事項。",
    "台灣觀點": "這些辦法是主管機關為落實商標代理人制度、確保服務品質所訂定的行政規則，是商標法在特定領域的具體化規範。"
  },
  {
    "關係代號": "LH_商標法_海關查扣辦法",
    "主法規": "商標法",
    "關聯法規": "海關查扣程序相關辦法",
    "階層關係類型": "下位行政規則",
    "關聯說明": "商標法第七十八條第一項授權主管機關會同財政部訂定辦法，規範海關執行商標權邊境保護措施中關於查扣程序、保證金等事項。",
    "台灣觀點": "這些辦法是商標法保障商標權人在邊境執法的具體行政程序規範，由跨部會（經濟部、財政部）會同訂定。"
  },
  {
    "關係代號": "LH_商標法_海關保護辦法",
    "主法規": "商標法",
    "關聯法規": "海關商標權保護措施辦法",
    "階層關係類型": "下位行政規則",
    "關聯說明": "商標法第七十八條第二項授權財政部訂定辦法，規範海關執行商標權邊境保護措施中關於權利人申請檢視、資訊提供、貨樣調借等相關事項。",
    "台灣觀點": "這些辦法是商標法賦予商標權人請求海關協助保護其權利時，需遵循的具體行政程序規範，屬於財政部權責範圍。"
  }
]