[
  {
    "代號": "LR_強制執行法_4_民事訴訟法",
    "關聯類型": "法條-法規",
    "主法規": "強制執行法",
    "主法規條號": "第四條",
    "關聯法規": "民事訴訟法",
    "關聯法規條號": null,
    "關聯說明": "定義民事強制執行之執行名義類型，包含依民事訴訟法得為強制執行之裁判、成立之和解或調解。",
    "台灣觀點": "本條連結《強制執行法》與《民事訴訟法》，確立了透過民事訴訟程序取得的特定法律文書（如判決、和解、調解）是進行強制執行的基礎。"
  },
  {
    "代號": "LR_強制執行法_4_公證法",
    "關聯類型": "法條-法規",
    "主法規": "強制執行法",
    "主法規條號": "第四條",
    "關聯法規": "公證法",
    "關聯法規條號": null,
    "關聯說明": "定義依公證法規定得為強制執行之公證書為民事強制執行之執行名義。",
    "台灣觀點": "台灣實務上，許多債權人會選擇透過公證方式取得具有強制執行效力的公證書，以便快速啟動執行程序，減輕訴訟負擔。本條是此一實務操作的法律依據。"
  },
  {
    "代號": "LR_強制執行法_4_民法",
    "關聯類型": "法條-法規",
    "主法規": "強制執行法",
    "主法規條號": "第四條",
    "關聯法規": "民法",
    "關聯法規條號": null,
    "關聯說明": "定義抵押權人或質權人聲請拍賣抵押物或質物之許可裁定為民事強制執行之執行名義。抵押權及質權為民法上之物權。",
    "台灣觀點": "本條連結《強制執行法》與《民法》上關於擔保物權（抵押權、質權）的規定，允許擔保物權人透過法院裁定，直接聲請拍賣擔保物以實現債權，是擔保物權的重要實現方式。"
  },
  {
    "代號": "LR_強制執行法_4-1_民事訴訟法",
    "關聯類型": "法條-法規",
    "主法規": "強制執行法",
    "主法規條號": "第四條之一",
    "關聯法規": "民事訴訟法",
    "關聯法規條號": "第四百零二條",
    "關聯說明": "規範依外國法院確定判決聲請強制執行者，需經中華民國法院許可，且該判決無民事訴訟法第四百零二條各款情形之一。",
    "台灣觀點": "本條涉及國際私法和法院管轄權問題，明確了外國法院判決在台灣的執行前提，即須符合《民事訴訟法》關於承認外國判決效力的條件，並經台灣法院裁定許可，體現了國家主權和對外國司法文書的審查機制。"
  },
  {
    "代號": "LR_強制執行法_4-2_民事訴訟法",
    "關聯類型": "法條-法規",
    "主法規": "強制執行法",
    "主法規條號": "第四條之二",
    "關聯法規": "民事訴訟法",
    "關聯法規條號": null,
    "關聯說明": "規範確定終局判決之執行名義效力所及之人，其規定準用民事訴訟法關於判決效力擴張之原則。",
    "台灣觀點": "本條擴張了執行名義的效力範圍，使其不僅限於判決當事人，也包括訴訟繫屬後的繼受人等，這與《民事訴訟法》中關於判決效力主觀範圍的原理相符，確保執行效果不因權利移轉而落空。"
  },
  {
    "代號": "LR_強制執行法_5_民法",
    "關聯類型": "法條-法規",
    "主法規": "強制執行法",
    "主法規條號": "第五條",
    "關聯法規": "民法",
    "關聯法規條號": null,
    "關聯說明": "規範債務人死亡後強制執行之續行，並提及遺囑執行人或遺產管理人之存在。這些身份與職責依民法規定。",
    "台灣觀點": "本條處理債務人死亡這一常見的執行障礙，透過選任特別代理人或由既有的遺囑執行人/遺產管理人接續執行程序，確保債權人的權益得以在繼承發生後繼續實現，與《民法》繼承編的規定相銜接。"
  },
  {
    "代號": "LR_強制執行法_5-1_民法",
    "關聯類型": "法條-法規",
    "主法規": "強制執行法",
    "主法規條號": "第五條之一",
    "關聯法規": "民法",
    "關聯法規條號": "第一百五十一條",
    "關聯說明": "規範債權人依民法第一百五十一條規定自行拘束債務人自由或押收財產，聲請法院處理者，依本法規定辦理。",
    "台灣觀點": "《民法》第一百五十一條賦予債權人在一定緊急情況下自行實現債權的權利（自力救濟），本條則明確了在這種情況下，後續由法院介入處理的程序，應回歸適用《強制執行法》，避免自力救濟的濫用，並確保程序合法性。"
  },
  {
    "代號": "LR_強制執行法_11_民法",
    "關聯類型": "法條-法規",
    "主法規": "強制執行法",
    "主法規條號": "第十一條",
    "關聯法規": "民法",
    "關聯法規條號": null,
    "關聯說明": "規範應登記事項之財產權執行時通知登記機關登記，以及債務人因繼承、法院判決取得不動產物權之登記後執行。繼承、不動產物權、法院判決等概念依民法或其他相關法規。",
    "台灣觀點": "本條涉及不動產執行中的登記問題，強調強制執行效力應透過登記公示，並處理了繼承登記等實務難題，確保執行程序的順暢進行，與《民法》物權編及繼承編、以及地政登記相關法規密切相關。"
  },
  {
    "代號": "LR_強制執行法_14_民事訴訟法",
    "關聯類型": "法條-法規",
    "主法規": "強制執行法",
    "主法規條號": "第十四條",
    "關聯法規": "民事訴訟法",
    "關聯法規條號": null,
    "關聯說明": "規範債務人異議之訴的提起事由（執行名義成立後發生消滅或妨礙請求之事由）及其程序，此訴訟程序準用民事訴訟法。",
    "台灣觀點": "異議之訴是債務人對執行名義提出實體上爭議的重要救濟途徑，本條確立了其提起條件與範圍，與《民事訴訟法》關於訴訟程序的規定相輔相成，保障債務人的程序權利。"
  },
  {
    "代號": "LR_強制執行法_15_民法",
    "關聯類型": "法條-法規",
    "主法規": "強制執行法",
    "主法規條號": "第十五條",
    "關聯法規": "民法",
    "關聯法規條號": null,
    "關聯說明": "規範第三人就執行標的物有足以排除強制執行之權利時，得提起異議之訴。此權利通常為民法上之物權或其他合法占有權源。",
    "台灣觀點": "第三人異議之訴是保護非債務人權益的重要機制，避免因強制執行錯誤地侵害第三人的合法權利。本條與《民法》上的物權、債權等概念緊密相關，確保了執行範圍的合法性。"
  },
  {
    "代號": "LR_強制執行法_18_民事訴訟法",
    "關聯類型": "法條-法規",
    "主法規": "強制執行法",
    "主法規條號": "第十八條",
    "關聯法規": "民事訴訟法",
    "關聯法規條號": null,
    "關聯說明": "規範強制執行原則上不因提起回復原狀、再審、異議之訴等停止，但法院得依聲請並定擔保停止執行。這些訴訟或程序依民事訴訟法規定。",
    "台灣觀點": "本條平衡了債權人迅速實現債權的利益與債務人或第三人尋求實體救濟的權利。停止執行的條件（提供擔保）是核心，與《民事訴訟法》中關於暫時狀態處分或停止執行程序的精神一致。"
  },
  {
    "代號": "LR_強制執行法_22-5_刑事訴訟法",
    "關聯類型": "法條-法規",
    "主法規": "強制執行法",
    "主法規條號": "第二十二條之五",
    "關聯法規": "刑事訴訟法",
    "關聯法規條號": null,
    "關聯說明": "規範拘提、管收準用刑事訴訟法關於拘提、羈押之規定。",
    "台灣觀點": "本條引入了刑事訴訟中限制人身自由的手段（拘提、管收）於民事執行程序，但為確保人權，特別規定準用《刑事訴訟法》的相關程序保障，如需法官簽發票證、符合法定事由等，體現了法律體系內不同領域規範的相互借鑒與限制。"
  },
  {
    "代號": "LR_強制執行法_23_民事訴訟法",
    "關聯類型": "法條-法規",
    "主法規": "強制執行法",
    "主法規條號": "第二十三條",
    "關聯法規": "民事訴訟法",
    "關聯法規條號": "第九十一條",
    "關聯說明": "規範債權人因強制執行支出費用得求償於債務人，並準用民事訴訟法第九十一條關於訴訟費用確定之規定。",
    "台灣觀點": "本條明確了執行費用由債務人負擔的原則，並透過準用《民事訴訟法》的費用確定程序，提供了執行費用數額的確定機制，確保了費用求償的合法性與程序性。"
  },
  {
    "代號": "LR_強制執行法_25_民法",
    "關聯類型": "法條-法規",
    "主法規": "強制執行法",
    "主法規條號": "第二十五條",
    "關聯法規": "民法",
    "關聯法規條號": null,
    "關聯說明": "規範債務人拘提、管收、限制住居等規定，於其法定代理人、繼承人、遺產管理人、遺囑執行人等亦適用之。這些身份依民法規定。",
    "台灣觀點": "本條擴大了執行階段應負義務者的範圍，將與債務人有特定身份關係的人（如繼承人、法定代理人）納入規範，確保在債務人本人無法履行義務時，仍有其他人可以代表或承擔相關責任，以利執行程序的進行。"
  },
  {
    "代號": "LR_強制執行法_30_民事訴訟法",
    "關聯類型": "法條-法規",
    "主法規": "強制執行法",
    "主法規條號": "第三十條",
    "關聯法規": "民事訴訟法",
    "關聯法規條號": null,
    "關聯說明": "規範依判決為強制執行，其判決經變更或廢棄時，受訴法院應命債權人償還強制執行費用。此乃民事訴訟法再審或上訴等程序影響執行結果之處理。",
    "台灣觀點": "本條處理了原執行名義（判決）被事後撤銷或變更時，執行程序如何回溯處理費用的問題，是《強制執行法》與《民事訴訟法》救濟程序相銜接的規定，保障了債務人在原執行名義失效後，有權要求返還不當支出的費用。"
  },
  {
    "代號": "LR_強制執行法_30-1_民事訴訟法",
    "關聯類型": "法規-法規",
    "主法規": "強制執行法",
    "主法規條號": null,
    "關聯法規": "民事訴訟法",
    "關聯法規條號": null,
    "關聯說明": "強制執行程序除本法有規定外，準用民事訴訟法之規定。",
    "台灣觀點": "這是《強制執行法》中最核心的準用條款，確立了民事執行程序與民事訴訟程序的緊密關聯性。在《強制執行法》未特別規定的事項，應回歸適用《民事訴訟法》的原理原則和具體規定，維持法體系的一致性。"
  },
  {
    "代號": "LR_強制執行法_33-1_行政執行法",
    "關聯類型": "法條-法規",
    "主法規": "強制執行法",
    "主法規條號": "第三十三條之一",
    "關聯法規": "行政執行法",
    "關聯法規條號": null,
    "關聯說明": "規範民事執行與行政執行機關就同一財產查封之協調處理，若行政執行機關已查封，民事執行法院不得再查封，應函送行政執行機關合併辦理。",
    "台灣觀點": "本條是為了解決民事與行政執行競合問題而設，避免重複查封造成困擾，並確立了行政執行機關在特定情況下的優先處理權，是公法與私法執行程序協調的重要規定。"
  },
  {
    "代號": "LR_強制執行法_33-2_行政執行法",
    "關聯類型": "法條-法規",
    "主法規": "強制執行法",
    "主法規條號": "第三十三條之二",
    "關聯法規": "行政執行法",
    "關聯法規條號": null,
    "關聯說明": "規範民事執行與行政執行機關就同一財產查封之協調處理，若民事執行法院已查封，行政執行機關不得再查封，應函送執行法院合併辦理。",
    "台灣觀點": "本條與前條互補，共同構成了民事與行政執行競合時的處理原則，確保同一財產的執行程序得以合併處理，提高效率並避免衝突，是台灣執行實務中常見的協調機制。"
  },
  {
    "代號": "LR_強制執行法_34_民法",
    "關聯類型": "法條-法規",
    "主法規": "強制執行法",
    "主法規條號": "第三十四條",
    "關聯法規": "民法",
    "關聯法規條號": null,
    "關聯說明": "規範依法對於執行標的物有擔保物權或優先受償權之債權人聲明參與分配。擔保物權及優先受償權依民法或其他法律規定。",
    "台灣觀點": "本條處理了有擔保或優先權債權人在強制執行程序中的權益保障問題，其權利的基礎來自於《民法》或其他特別法，本法則規範他們如何在執行程序中主張並實現這些權利，體現了執行程序對實體法權利的尊重與實現功能。"
  },
  {
    "代號": "LR_強制執行法_34-1_行政執行法",
    "關聯類型": "法條-法規",
    "主法規": "強制執行法",
    "主法規條號": "第三十四條之一",
    "關聯法規": "行政執行法",
    "關聯法規條號": null,
    "關聯說明": "規範政府機關有公法上金錢債權，依行政執行法得移送執行者，得聲明參與分配。",
    "台灣觀點": "本條允許政府機關將其公法債權（如稅款、罰鍰）納入民事執行程序的分配，是公法債權實現的一種方式，與《行政執行法》中關於公法債權移送執行的規定相呼應，確保政府債權的實現途徑。"
  },
  {
    "代號": "LR_強制執行法_59_刑法",
    "關聯類型": "法條-法規",
    "主法規": "強制執行法",
    "主法規條號": "第五十九條",
    "關聯法規": "刑法",
    "關聯法規條號": null,
    "關聯說明": "規範查封物交保管人時，應告知刑法所定損壞、除去或污穢查封標示或為違背其效力之行為之處罰。",
    "台灣觀點": "本條引用《刑法》的規定，藉由告知刑事責任來強化對查封物的保護，確保強制執行程序的順利進行，是民事執行程序藉助刑事法威嚇力的一個例子。"
  },
  {
    "代號": "LR_強制執行法_98_民法",
    "關聯類型": "法條-法規",
    "主法規": "強制執行法",
    "主法規條號": "第九十八條",
    "關聯法規": "民法",
    "關聯法規條號": null,
    "關聯說明": "規範拍賣不動產後買受人取得所有權之時點及其上原有地上權、抵押權等物權或租賃關係之存續或消滅。這些權利依民法規定。",
    "台灣觀點": "本條是強制執行法中關於不動產拍賣「權利淨化」的核心條款，明確了拍定後不動產上既存權利的處理原則（原則上消滅抵押權等，部分用益物權及租賃權隨同移轉），對不動產交易安全和買受人權益保障至關重要，與《民法》物權編及債權編的規定息息相關。"
  },
  {
    "代號": "LR_強制執行法_114_海商法",
    "關聯類型": "法條-法規",
    "主法規": "強制執行法",
    "主法規條號": "第一百十四條",
    "關聯法規": "海商法",
    "關聯法規條號": null,
    "關聯說明": "規範海商法所定之船舶強制執行，準用關於不動產執行之規定。並就船舶執行之特定時點及保全程序執行名義設例外規定。",
    "台灣觀點": "本條將船舶執行準用不動產執行的規定，同時考量船舶作為特殊動產的特性（如航行中），設有特別規範，並與《海商法》中關於船舶執行、優先權等規定相配合，是海事執行獨特性的體現。"
  },
  {
    "代號": "LR_強制執行法_114-1_海商法",
    "關聯類型": "法條-法規",
    "主法規": "強制執行法",
    "主法規條號": "第一百十四條之一",
    "關聯法規": "海商法",
    "關聯法規條號": "第二十四條第一項第一款",
    "關聯說明": "規範船舶查封後應取去國籍文書並停泊，但允許航行之例外情形不影響海商法第二十四條第一項第一款之優先受償權。",
    "台灣觀點": "此條細化了船舶查封後的管理和例外情況，並明確了特定海事優先權的優先性，是海事執行程序中的重要細節規範，與《海商法》的海事優先權制度緊密相關。"
  },
  {
    "代號": "LR_強制執行法_114-3_海商法",
    "關聯類型": "法條-法規",
    "主法規": "強制執行法",
    "主法規條號": "第一百十四條之三",
    "關聯法規": "海商法",
    "關聯法規條號": null,
    "關聯說明": "規範外國船舶經中華民國法院拍賣者，關於船舶之優先權及抵押權依船籍國法。",
    "台灣觀點": "本條處理了涉外海事執行的法律適用問題，明確了外國船舶的優先權和抵押權應依其船籍國法決定，體現了國際私法在海事執行領域的適用原則，並與《海商法》的相關規定相協調。"
  },
  {
    "代號": "LR_強制執行法_114-4_民用航空法",
    "關聯類型": "法條-法規",
    "主法規": "強制執行法",
    "主法規條號": "第一百十四條之四",
    "關聯法規": "民用航空法",
    "關聯法規條號": null,
    "關聯說明": "規範民用航空法所定航空器之強制執行，準用關於船舶執行之規定。",
    "台灣觀點": "本條將航空器執行準用船舶執行的規定，考量了航空器作為特殊動產與船舶的相似性，同時也需與《民用航空法》中關於航空器登記、抵押等規定配合，是航空器執行程序的主要依據。"
  },
  {
    "代號": "LR_強制執行法_122_社會福利相關法規",
    "關聯類型": "法條-法規",
    "主法規": "強制執行法",
    "主法規條號": "第一百二十二條",
    "關聯法規": "社會福利、社會救助、社會保險相關法規",
    "關聯法規條號": null,
    "關聯說明": "規範依法領取之社會福利津貼、社會救助或補助、社會保險給付等不得為強制執行之範圍，並提及最低生活費標準依衛生福利部或直轄市政府公告。",
    "台灣觀點": "本條基於保障債務人及其共同生活親屬基本生存權的理念，明文排除部分與維持生活密切相關的收入或財產免於執行，是《強制執行法》人道精神的體現，與台灣各項社會福利、社會救助及社會保險制度的立法目的相符。"
  },
  {
    "代號": "LR_強制執行法_122-1_行政執行法",
    "關聯類型": "法條-法規",
    "主法規": "強制執行法",
    "主法規條號": "第一百二十二條之一",
    "關聯法規": "行政執行法",
    "關聯法規條號": null,
    "關聯說明": "規範公法人為債務人之金錢請求權執行，原則上適用本節規定，但不適用關於拘提、管收等規定。本節為處理公法人執行之特別規定。",
    "台灣觀點": "本條確立了對公法人（如政府機關、公營事業）進行金錢債權執行時的特殊程序，有別於對一般私人的執行，考量了公法人執行職務的公共性，並明文排除對公法人負責人的拘提、管收，體現了對公權力運作的必要尊重與限制。"
  },
  {
    "代號": "LR_強制執行法_122-4_國有財產法_土地法_其他法令",
    "關聯類型": "法條-法規",
    "主法規": "強制執行法",
    "主法規條號": "第一百二十二條之四",
    "關聯法規": "國有財產法、土地法及其他法令",
    "關聯法規條號": null,
    "關聯說明": "規範債務人為公法人時，其管有之非公用財產及不屬於第一百二十二條之三第一項之公用財產，仍得為強制執行，不受國有財產法、土地法及其他法令有關處分規定之限制。",
    "台灣觀點": "本條是針對公法人執行程序的關鍵條款，明確了公法人財產中非供公用或非必需的部分仍可被強制執行，並優先於《國有財產法》、《土地法》等關於公有財產處分限制的規定，平衡了債權人權益與公法人財產管理的特殊性。"
  },
  {
    "代號": "LR_強制執行法_128_民法",
    "關聯類型": "法條-法規",
    "主法規": "強制執行法",
    "主法規條號": "第一百二十八條",
    "關聯法規": "民法",
    "關聯法規條號": null,
    "關聯說明": "規範命債務人為一定行為而非他人所能代履行者之執行方法（怠金、管收），並提及夫妻同居判決不適用本條規定。夫妻同居義務依民法規定。",
    "台灣觀點": "本條處理了「非替代性行為」債務的執行困境，透過間接強制（怠金、管收）促使債務人履行，但特別排除涉及人身自由或情感關係的夫妻同居判決，體現了強制執行手段的界限，與《民法》親屬編的特定規定相呼應。"
  },
  {
    "代號": "LR_強制執行法_131_民法",
    "關聯類型": "法條-法規",
    "主法規": "強制執行法",
    "主法規條號": "第一百三十一條",
    "關聯法規": "民法",
    "關聯法規條號": null,
    "關聯說明": "規範關於繼承財產或共有物分割之裁判的執行方法。繼承及共有依民法規定。",
    "台灣觀點": "本條為繼承和共有關係結束後，依法院裁判進行財產分配或變價分配提供了執行依據，是《強制執行法》處理共有關係消滅執行問題的具體規定，與《民法》物權編及繼承編密切相關。"
  },
  {
    "代號": "LR_強制執行法_132_民事訴訟法",
    "關聯類型": "法條-法規",
    "主法規": "強制執行法",
    "主法規條號": "第一百三十二條",
    "關聯法規": "民事訴訟法",
    "關聯法規條號": null,
    "關聯說明": "規範假扣押或假處分之執行時點及程序，假扣押、假處分之裁定依民事訴訟法規定。",
    "台灣觀點": "本條是保全程序執行（假扣押、假處分）的重要程序規定，強調執行的即時性，並與《民事訴訟法》中關於保全程序的裁定緊密相連，確保債權人在訴訟確定前能有效保全其權利。"
  },
  {
    "代號": "LR_強制執行法_140_民事訴訟法",
    "關聯類型": "法條-法規",
    "主法規": "強制執行法",
    "主法規條號": "第一百四十條",
    "關聯法規": "民事訴訟法",
    "關聯法規條號": null,
    "關聯說明": "規範假處分之執行，除本章特別規定外，準用關於假扣押、金錢請求權及行為、不行為請求權執行之規定。這些執行方法部分源自或準用民事訴訟法。",
    "台灣觀點": "本條透過準用其他執行類型的規定，簡化了假處分執行的規範，使其與本法其他執行程序以及《民事訴訟法》的相關規定保持一致性。"
  }
]